ironSourceAtom
