Metadata-Version: 1.1
Name: ironSourceAtom
Version: 1.0.4
Summary: ironSource.atom Python SDK
Home-page: https://github.com/ironSource/atom-python
Author: ironSource.atom
Author-email: atom@ironsrc.com
License: MIT
Platform: UNKNOWN
Classifier: Development Status :: 5 - Production/Stable
Classifier: Intended Audience :: Developers
Classifier: Natural Language :: English
Classifier: License :: OSI Approved :: Apache Software License
Classifier: Programming Language :: Python
Classifier: Programming Language :: Python :: 2.7
Classifier: Programming Language :: Python :: 3
Classifier: Programming Language :: Python :: 3.3
Classifier: Programming Language :: Python :: 3.4
Classifier: Programming Language :: Python :: 3.5
